Metadata-Version: 2.1
Name: redis-tools-py2
Version: 0.0.2
Summary: Library for inter-service event-based communication
Home-page: https://github.com/radiocut/redis-tools/
Author: Guillermo Narvaja
Author-email: guillermo.narvaja@radiocut.fm
License: UNKNOWN
Project-URL: Bug Reports, https://github.com/radiocutfm/redis-tools/issues
Project-URL: Funding, https://donate.pypi.org
Project-URL: Say Thanks!, https://saythanks.io/to/guillermo.narvaja%40radiocut.fm
Project-URL: Source, https://github.com/radiocutfm/redis-tools/
Keywords: redis rate-limit
Platform: UNKNOWN
Classifier: Development Status :: 3 - Alpha
Classifier: Intended Audience :: Developers
Classifier: License :: OSI Approved :: MIT License
Classifier: Programming Language :: Python :: 2.7
Requires-Python: >=2.7, <3
Requires-Dist: environs (<5)
Requires-Dist: redis
Provides-Extra: dev
Requires-Dist: check-manifest ; extra == 'dev'
Provides-Extra: test
Requires-Dist: coverage ; extra == 'test'
Requires-Dist: redislite ; extra == 'test'
Requires-Dist: mock ; extra == 'test'
